everystamp/__init__.py
everystamp/cutters.py
everystamp/downloaders.py
everystamp/everystamp.py
everystamp/plotters.py
everystamp/tonemapping/__init__.py
everystamp/tonemapping/lhdr.py
everystamp-1.6.1.dist-info/METADATA
everystamp-1.6.1.dist-info/WHEEL
everystamp-1.6.1.dist-info/entry_points.txt
everystamp-1.6.1.dist-info/top_level.txt
everystamp-1.6.1.dist-info/RECORD
