Metadata-Version: 2.4
Name: EveryStamp
Version: 1.6.1
Summary: A Python interface for retrieving FITS or image cutouts from a variety of astronomical surveys.
Author: Frits Sweijen
Project-URL: Homepage, https://tikk3r.github.io/EveryStamp/
Project-URL: Bug Tracker, https://github.com/tikk3r/EveryStamp/issues
Classifier: Programming Language :: Python :: 3
Classifier: License :: OSI Approved :: GNU General Public License v3 (GPLv3)
Classifier: Operating System :: OS Independent
Classifier: Topic :: Scientific/Engineering :: Astronomy
Requires-Python: >=3.9
Requires-Dist: astropy
Requires-Dist: aplpy
Requires-Dist: astroquery
Requires-Dist: blend-modes
Requires-Dist: colormaps
Requires-Dist: matplotlib
Requires-Dist: markupsafe
Requires-Dist: numpy<2
Requires-Dist: panstamps
Requires-Dist: Pillow
Requires-Dist: opencv-python-headless
Requires-Dist: pyavm
Requires-Dist: python-magic
Requires-Dist: pyvo
Requires-Dist: requests
Requires-Dist: scikit-image
Requires-Dist: tqdm
